{
  "users": [
    {
      "email": "Drogba11144@gmail.com",
      "password": "$2a$10$4fKLh707f0nwgu0Pd7moEuwj4yXkTzZfYXm8WKIxuTaHFjrgc.pvm",
      "firstname": "Patrik",
      "lastname": "Villant",
      "bio": "",
      "image": "/assets/user_default.png",
      "id": 1
    },
    {
      "email": "helenka1112@gmail.com",
      "password": "$2a$10$WazN2Xf3wKRBn4a5FMWwjeE/nb0Q9cne7mO4/P5pJxIKbzs6eivWu",
      "firstname": "Helena",
      "lastname": "Labužníková",
      "bio": "",
      "image": "/assets/user_default.png",
      "id": 2
    }
  ],
  "posts": [
    {
      "name": "dobre bude",
      "ingredients": [
        "dasdasd"
      ],
      "recipe": "dasdasdasdasdasd",
      "profile": {
        "email": "Drogba11144@gmail.com",
        "password": "$2a$10$4fKLh707f0nwgu0Pd7moEuwj4yXkTzZfYXm8WKIxuTaHFjrgc.pvm",
        "firstname": "Patrik",
        "lastname": "Villant",
        "bio": "",
        "image": "/assets/user_default.png",
        "id": 1
      },
      "userid": 1,
      "id": 1
    },
    {
      "name": "potkan",
      "ingredients": [
        "asdasd"
      ],
      "recipe": "dasdfasdasdasd",
      "profile": {
        "email": "helenka1112@gmail.com",
        "password": "$2a$10$WazN2Xf3wKRBn4a5FMWwjeE/nb0Q9cne7mO4/P5pJxIKbzs6eivWu",
        "firstname": "Helena",
        "lastname": "Labužníková",
        "bio": "",
        "image": "/assets/user_default.png",
        "id": 2
      },
      "userid": 2,
      "id": 2
    }
  ],
  "comments": []
}